ipv4mutate.py
ipv4mutate-0.9.1.dist-info/LICENSE
ipv4mutate-0.9.1.dist-info/METADATA
ipv4mutate-0.9.1.dist-info/WHEEL
ipv4mutate-0.9.1.dist-info/top_level.txt
ipv4mutate-0.9.1.dist-info/RECORD
