Metadata-Version: 2.1
Name: ipv4mutate
Version: 0.9.1
Summary: performs various mutations on IPv4 addresses, such as converting to hex, octal, urlencoded, and more
Home-page: https://github.com/bonifield/IPv4Mutate
Author: James Bonifield
Author-email: bonifield.tools@gmail.com
License: UNKNOWN
Platform: UNKNOWN
Classifier: Programming Language :: Python :: 3
Classifier: License :: OSI Approved :: MIT License
Classifier: Operating System :: OS Independent
License-File: LICENSE
